pikta_calendar/__init__.py
pikta_calendar/consult_service.py
pikta_calendar/pikta_calendar.py
pikta_calendar-0.1.0.dist-info/LICENSE
pikta_calendar-0.1.0.dist-info/WHEEL
pikta_calendar-0.1.0.dist-info/METADATA
pikta_calendar-0.1.0.dist-info/RECORD
