Metadata-Version: 2.1
Name: pikta_calendar
Version: 0.1.0
Summary: Production calendar from www.consultant.ru
Home-page: https://github.com/stigsanek/pikta-calendar
Author: Aleksandr Egorov
Author-email: stigsanek@yandex.ru
Classifier: License :: OSI Approved :: MIT License
